[
    {
        "actionName": "Action",
        "steps": [
            {
                "stepId": "STEP17",
                "stepName": "Url: WebTours",
                "infFile": "t2.inf",
                "time": 1600415580508
            },
            {
                "stepId": "STEP18",
                "stepName": "Submit Data: login.pl",
                "infFile": "t3.inf",
                "time": 1600415581052
            },
            {
                "stepId": "STEP19",
                "stepName": "Url: Search Flights Button",
                "infFile": "t4.inf",
                "time": 1600415581508
            },
            {
                "stepId": "STEP20",
                "stepName": "Submit Data: reservations.pl",
                "infFile": "t6.inf",
                "time": 1600415581861
            },
            {
                "stepId": "STEP21",
                "stepName": "Submit Data: reservations.pl_2",
                "infFile": "t7.inf",
                "time": 1600415582119
            },
            {
                "stepId": "STEP22",
                "stepName": "Submit Data: reservations.pl_3",
                "infFile": "t8.inf",
                "time": 1600415582652
            },
            {
                "stepId": "STEP23",
                "stepName": "Url: Itinerary Button",
                "infFile": "t9.inf",
                "time": 1600415583273
            },
            {
                "stepId": "STEP24",
                "stepName": "Url: SignOff Button",
                "infFile": "t10.inf",
                "time": 1600415583855
            }
        ],
        "transactions": [
            {
                "transactionName": "Gotosite",
                "rawStartTime": 1600415579991,
                "rawEndTime": 1600415580514,
                "thinkTime": 0.0,
                "wastedTime": 0.1941978931427002
            },
            {
                "transactionName": "login",
                "rawStartTime": 1600415580516,
                "rawEndTime": 1600415581053,
                "thinkTime": 0.0,
                "wastedTime": 0.15650367736816407
            },
            {
                "transactionName": "click_flights",
                "rawStartTime": 1600415581054,
                "rawEndTime": 1600415581513,
                "thinkTime": 0.0,
                "wastedTime": 0.14110445976257325
            },
            {
                "transactionName": "fill_find_flights",
                "rawStartTime": 1600415581515,
                "rawEndTime": 1600415581862,
                "thinkTime": 0.0,
                "wastedTime": 0.09593081474304199
            },
            {
                "transactionName": "choose_flight",
                "rawStartTime": 1600415581865,
                "rawEndTime": 1600415582121,
                "thinkTime": 0.0,
                "wastedTime": 0.05015730857849121
            },
            {
                "transactionName": "fill_payment",
                "rawStartTime": 1600415582123,
                "rawEndTime": 1600415582655,
                "thinkTime": 0.0,
                "wastedTime": 0.17218565940856934
            },
            {
                "transactionName": "click_itinerary",
                "rawStartTime": 1600415582657,
                "rawEndTime": 1600415583275,
                "thinkTime": 0.0,
                "wastedTime": 0.17438888549804688
            },
            {
                "transactionName": "logout",
                "rawStartTime": 1600415583278,
                "rawEndTime": 1600415583856,
                "thinkTime": 0.0,
                "wastedTime": 0.19024276733398438
            },
            {
                "transactionName": "UC_1_form_ticket_and_itin",
                "rawStartTime": 1600415579990,
                "rawEndTime": 1600415583858,
                "thinkTime": 0.0,
                "wastedTime": 1.1747114658355713
            }
        ]
    }
]